bisslog_fastapi/__init__.py
bisslog_fastapi/builder/__init__.py
bisslog_fastapi/builder/builder_fastapi_app_manager.py
bisslog_fastapi/builder/static_python_construct_data.py
bisslog_fastapi/builder/strategies/__init__.py
bisslog_fastapi/builder/strategies/trigger_http_processor.py
bisslog_fastapi/builder/strategies/trigger_processor.py
bisslog_fastapi/builder/strategies/trigger_ws_processor.py
bisslog_fastapi/cli/__init__.py
bisslog_fastapi/cli/commands/__init__.py
bisslog_fastapi/cli/commands/build.py
bisslog_fastapi/cli/commands/run.py
bisslog_fastapi/runner/__init__.py
bisslog_fastapi/runner/fastapi_http_resolver.py
bisslog_fastapi/runner/fastapi_resolver.py
bisslog_fastapi/runner/fastapi_ws_resolver.py
bisslog_fastapi/runner/init_fastapi_app.py
bisslog_fastapi/utils/__init__.py
bisslog_fastapi/utils/extract_path_vars.py
bisslog_fastapi/utils/get_param_type.py
bisslog_fastapi/utils/infer_response_model.py
bisslog_fastapi/utils/type_to_str_and_imports.py
bisslog_fastapi-0.0.1.dist-info/licenses/LICENSE
bisslog_fastapi-0.0.1.dist-info/METADATA
bisslog_fastapi-0.0.1.dist-info/WHEEL
bisslog_fastapi-0.0.1.dist-info/entry_points.txt
bisslog_fastapi-0.0.1.dist-info/top_level.txt
bisslog_fastapi-0.0.1.dist-info/RECORD
