Metadata-Version: 2.4
Name: bisslog_fastapi
Version: 0.0.1
Summary: Framework-agnostic adapter for Bisslog. Connects external interfaces to use cases while keeping domain logic isolated and pure.
Author-email: Darwin Stiven Herrera Cartagena <darwinsherrerac@gmail.com>
Project-URL: Homepage, https://github.com/darwinhc/bisslog-fastapi
Keywords: hexagonal,adapters,bisslog,fastapi
Classifier: Programming Language :: Python :: 3
Classifier: Operating System :: OS Independent
Requires-Python: >=3.8
License-File: LICENSE
Requires-Dist: bisslog>=0.0.9
Requires-Dist: bisslog-schema>=0.0.10
Requires-Dist: fastapi
Dynamic: license-file
